graphene_prometheus/__init__.py
graphene_prometheus/middleware.py
graphene_prometheus/py.typed
graphene_prometheus-0.1.0.dist-info/LICENSE
graphene_prometheus-0.1.0.dist-info/WHEEL
graphene_prometheus-0.1.0.dist-info/METADATA
graphene_prometheus-0.1.0.dist-info/RECORD
